imap/__init__.py
imap/editor.py
imap/global_var.py
imap/main.py
imap/map.py
imap/lib/__init__.py
imap/lib/common.py
imap/lib/convertor.py
imap/lib/convex_hull.py
imap/lib/draw.py
imap/lib/odr_spiral.py
imap/lib/polynoms.py
imap/lib/proj_helper.py
imap/lib/proto_utils.py
imap/lib/transform.py
imap/lib/opendrive/__init__.py
imap/lib/opendrive/common.py
imap/lib/opendrive/header.py
imap/lib/opendrive/junction.py
imap/lib/opendrive/lanes.py
imap/lib/opendrive/map.py
imap/lib/opendrive/plan_view.py
imap/lib/opendrive/profile.py
imap/lib/opendrive/road.py
imap/lib/opendrive/signals.py
imap/lib/opendrive/user_data.py
imap_box-0.1.10.dist-info/licenses/LICENSE
imap_box-0.1.10.dist-info/METADATA
imap_box-0.1.10.dist-info/WHEEL
imap_box-0.1.10.dist-info/entry_points.txt
imap_box-0.1.10.dist-info/top_level.txt
imap_box-0.1.10.dist-info/RECORD
