Metadata-Version: 2.4
Name: imap_box
Version: 0.1.10
Summary: High-resolution map visualization and conversion tool
Author-email: daohu527 <daohu527@gmail.com>
License: Apache Software License
Project-URL: Homepage, https://github.com/daohu527/imap
Project-URL: Bug Tracker, https://github.com/daohu527/imap/issues
Keywords: imap,mapping,visualization
Classifier: Programming Language :: Python :: 3
Classifier: License :: OSI Approved :: Apache Software License
Classifier: Operating System :: OS Independent
Requires-Python: >=3.6
License-File: LICENSE
Requires-Dist: protobuf<=3.19.4
Requires-Dist: matplotlib
Requires-Dist: pyproj
Requires-Dist: record_msg<=0.1.1
Dynamic: license-file
